{
  "_class": "group",
  "booleanOperation": 0,
  "clippingMaskMode": 0,
  "do_objectID": "388D6743-8CF0-48A0-9513-5C386E2BF646",
  "exportOptions": {
    "_class": "exportOptions",
    "do_objectID": "BAC3E704-C8FE-434B-8C1B-AC089A1A0F2A",
    "exportFormats": [
    ],
    "includedLayerIds": [
    ],
    "layerOptions": 0,
    "shouldTrim": false
  },
  "frame": {
    "_class": "rect",
    "constrainProportions": false,
    "do_objectID": "62A933DB-B573-4C99-849F-E379846B57EE",
    "height": 21,
    "width": 228.4497041420118,
    "x": 0,
    "y": 0
  },
  "hasClickThrough": false,
  "hasClippingMask": false,
  "isFixedToViewport": false,
  "isFlippedHorizontal": false,
  "isFlippedVertical": false,
  "isLocked": false,
  "isVisible": true,
  "layerListExpandedType": 0,
  "layers": [
    {
      "class": "group",
      "id": "36D4A25D-E9D8-43CE-AC05-BDEA0F015B6C"
    }
  ],
  "name": "Input",
  "nameIsFixed": true,
  "resizingConstraint": 63,
  "resizingType": 0,
  "rotation": 0,
  "shouldBreakMaskChain": false,
  "style": {
    "_class": "style",
    "do_objectID": "2D9F6FAD-BFE7-4AB1-B448-913F0961B138",
    "endMarkerType": 0,
    "miterLimit": 10,
    "startMarkerType": 0,
    "windingRule": 1
  },
  "userInfo": {
    "com.animaapp.stc-sketch-plugin": {
      "kModelPropertiesKey": {
        "align": 5,
        "isCollapsing": 1,
        "spacing": 2,
        "type": 1
      },
      "kViewTypeKey": "ADModelStackView"
    }
  }
}