{
  "_class": "group",
  "booleanOperation": 0,
  "clippingMaskMode": 0,
  "do_objectID": "DD845417-E67B-4C11-BD0C-79BD56928A79",
  "exportOptions": {
    "_class": "exportOptions",
    "do_objectID": "EB84BBEA-368D-4061-BCD0-24678045CFD3",
    "exportFormats": [
    ],
    "includedLayerIds": [
    ],
    "layerOptions": 0,
    "shouldTrim": false
  },
  "frame": {
    "_class": "rect",
    "constrainProportions": false,
    "do_objectID": "A4603850-265A-447A-B1C6-CE0DC3410BFF",
    "height": 238,
    "width": 510,
    "x": 0,
    "y": 28
  },
  "hasClickThrough": false,
  "hasClippingMask": false,
  "isFixedToViewport": false,
  "isFlippedHorizontal": false,
  "isFlippedVertical": false,
  "isLocked": false,
  "isVisible": true,
  "layerListExpandedType": 2,
  "layers": [
    {
      "class": "symbolInstance",
      "id": "4F8F3467-5B68-4F0B-8F1C-70EAEAA5BF2A"
    }
  ],
  "name": "⛔️ Don't Change",
  "nameIsFixed": false,
  "resizingConstraint": 63,
  "resizingType": 0,
  "rotation": 0,
  "shouldBreakMaskChain": false,
  "style": {
    "_class": "style",
    "do_objectID": "E4F77AA8-B726-4ABD-A72E-CA10C1A8A13A",
    "endMarkerType": 0,
    "miterLimit": 10,
    "startMarkerType": 0,
    "windingRule": 1
  },
  "userInfo": {
    "com.animaapp.stc-sketch-plugin": {
      "kModelPropertiesKey": {
      }
    }
  }
}