{
  "_class": "shapePath",
  "booleanOperation": -1,
  "clippingMaskMode": 0,
  "do_objectID": "B67AB8EB-C824-486A-8F69-A39AFFD95E3D",
  "edited": true,
  "exportOptions": {
    "_class": "exportOptions",
    "do_objectID": "5443239B-1526-44FF-BC8A-30ED100BFDE6",
    "exportFormats": [
    ],
    "includedLayerIds": [
    ],
    "layerOptions": 0,
    "shouldTrim": false
  },
  "frame": {
    "_class": "rect",
    "constrainProportions": false,
    "do_objectID": "082FB3A4-4012-4288-8249-FD52CF06DE92",
    "height": 23.63575,
    "width": 17.85075,
    "x": 1.636749999999999,
    "y": 20.02825
  },
  "hasClippingMask": false,
  "isClosed": true,
  "isFixedToViewport": false,
  "isFlippedHorizontal": false,
  "isFlippedVertical": false,
  "isLocked": false,
  "isVisible": true,
  "layerListExpandedType": 1,
  "name": "Shape",
  "nameIsFixed": false,
  "pointRadiusBehaviour": 1,
  "points": [
    {
      "_class": "curvePoint",
      "cornerRadius": 0,
      "curveFrom": "{0.41386216265423031, 0.90608506182372017}",
      "curveMode": 4,
      "curveTo": "{0.83017520272257495, 0.69147372095237081}",
      "hasCurveFrom": true,
      "hasCurveTo": true,
      "point": "{0.81161855944428107, 1}"
    },
    {
      "_class": "curvePoint",
      "cornerRadius": 0,
      "curveFrom": "{0.084408218142094898, 0.42139555546153601}",
      "curveMode": 4,
      "curveTo": "{0.13485427783146356, 0.78550500830310022}",
      "hasCurveFrom": true,
      "hasCurveTo": true,
      "point": "{0, 0.66289413282844833}"
    },
    {
      "_class": "curvePoint",
      "cornerRadius": 0,
      "curveFrom": "{0.58849067966331947, 0.055435093026453414}",
      "curveMode": 4,
      "curveTo": "{0.22532666694676695, 0.19764551579704479}",
      "hasCurveFrom": true,
      "hasCurveTo": true,
      "point": "{0.41304987185412373, 0}"
    },
    {
      "_class": "curvePoint",
      "cornerRadius": 0,
      "curveFrom": "{0.89576068232427231, 0.4025152576076495}",
      "curveMode": 4,
      "curveTo": "{0.78458888282004957, 0.1038680811905693}",
      "hasCurveFrom": true,
      "hasCurveTo": true,
      "point": "{1, 0.14347968649186083}"
    }
  ],
  "resizingConstraint": 63,
  "resizingType": 0,
  "rotation": 0,
  "shouldBreakMaskChain": false,
  "style": {
    "_class": "style",
    "blur": {
      "_class": "blur",
      "center": "{0.5, 0.5}",
      "do_objectID": "5905C932-02D9-40AB-95DB-7C9677826BFD",
      "isEnabled": false,
      "motionAngle": 0,
      "radius": 2.5,
      "saturation": 1,
      "type": 0
    },
    "do_objectID": "0468C409-946E-4E16-B570-073907D77160",
    "endMarkerType": 0,
    "fills": [
      {
        "_class": "fill",
        "color": {
          "_class": "color",
          "alpha": 1,
          "blue": 0.9803921568627451,
          "green": 0.9803921568627451,
          "red": 0.9803921568627451
        },
        "fillType": 0,
        "isEnabled": true,
        "noiseIndex": 0,
        "noiseIntensity": 0,
        "patternFillType": 1,
        "patternTileScale": 1
      }
    ],
    "miterLimit": 10,
    "startMarkerType": 0,
    "windingRule": 0
  }
}