{
  "_class": "shapePath",
  "booleanOperation": -1,
  "clippingMaskMode": 0,
  "do_objectID": "D013CC02-4302-456D-B045-0A7E9E598C17",
  "edited": true,
  "exportOptions": {
    "_class": "exportOptions",
    "do_objectID": "C6049D5F-FF68-43F1-93F0-979604ADDAF8",
    "exportFormats": [
    ],
    "includedLayerIds": [
    ],
    "layerOptions": 0,
    "shouldTrim": false
  },
  "frame": {
    "_class": "rect",
    "constrainProportions": false,
    "do_objectID": "61DE6E8F-63EF-411D-B7B8-2120F0CED9E4",
    "height": 12.11449999999999,
    "width": 15.12425,
    "x": 36.20900000000006,
    "y": 110.309
  },
  "hasClippingMask": false,
  "isClosed": true,
  "isFixedToViewport": false,
  "isFlippedHorizontal": false,
  "isFlippedVertical": false,
  "isLocked": false,
  "isVisible": true,
  "layerListExpandedType": 1,
  "name": "Shape",
  "nameIsFixed": false,
  "pointRadiusBehaviour": 1,
  "points": [
    {
      "_class": "curvePoint",
      "cornerRadius": 0,
      "curveFrom": "{0.27130270922525096, 0.54845433158611612}",
      "curveMode": 4,
      "curveTo": "{0.26310395556804417, 0.088179454372859525}",
      "hasCurveFrom": true,
      "hasCurveTo": true,
      "point": "{0, 0}"
    },
    {
      "_class": "curvePoint",
      "cornerRadius": 0,
      "curveFrom": "{1, 1}",
      "curveMode": 4,
      "curveTo": "{0.6171049804122517, 0.9141318254983708}",
      "hasCurveFrom": false,
      "hasCurveTo": true,
      "point": "{1, 1}"
    },
    {
      "_class": "curvePoint",
      "cornerRadius": 0,
      "curveFrom": "{0.94128634477742712, 0.13250650047463775}",
      "curveMode": 4,
      "curveTo": "{1, 0.12848239712740936}",
      "hasCurveFrom": true,
      "hasCurveTo": false,
      "point": "{1, 0.12848239712740936}"
    },
    {
      "_class": "curvePoint",
      "cornerRadius": 0,
      "curveFrom": "{0.53829115493330226, 0.13958479508027599}",
      "curveMode": 3,
      "curveTo": "{0.88321734962064236, 0.13958479508027599}",
      "hasCurveFrom": true,
      "hasCurveTo": true,
      "point": "{0.82367720713423809, 0.13958479508027599}"
    }
  ],
  "resizingConstraint": 63,
  "resizingType": 0,
  "rotation": 0,
  "shouldBreakMaskChain": false,
  "style": {
    "_class": "style",
    "blur": {
      "_class": "blur",
      "center": "{0.5, 0.5}",
      "do_objectID": "B7149137-3833-4EC2-9432-AD681A4DEEF3",
      "isEnabled": false,
      "motionAngle": 0,
      "radius": 2.5,
      "saturation": 1,
      "type": 0
    },
    "do_objectID": "88959263-36D4-4A9D-8FAA-93870057401D",
    "endMarkerType": 0,
    "fills": [
      {
        "_class": "fill",
        "color": {
          "_class": "color",
          "alpha": 1,
          "blue": 1,
          "green": 0.8360558712121212,
          "red": 0.8614954774033438
        },
        "fillType": 0,
        "isEnabled": true,
        "noiseIndex": 0,
        "noiseIntensity": 0,
        "patternFillType": 1,
        "patternTileScale": 1
      }
    ],
    "miterLimit": 10,
    "startMarkerType": 0,
    "windingRule": 0
  }
}